spikit/__init__.py
spikit/cli.py
spikit/config.ini
spikit/core.py
spikit/core_example.py
spikit/setup.py
spikit-0.1.5.dist-info/entry_points.txt
spikit-0.1.5.dist-info/WHEEL
spikit-0.1.5.dist-info/METADATA
spikit-0.1.5.dist-info/RECORD
